impute_test/__init__.py
impute_test/test.py
impute_test-0.0.1.dist-info/LICENSE
impute_test-0.0.1.dist-info/WHEEL
impute_test-0.0.1.dist-info/METADATA
impute_test-0.0.1.dist-info/RECORD
